swim/PackageDescription.swift
swim/__init__.py
swim/builder.py
swim/downloader.py
swim/package.py
swim-0.1.2.dist-info/DESCRIPTION.rst
swim-0.1.2.dist-info/METADATA
swim-0.1.2.dist-info/RECORD
swim-0.1.2.dist-info/WHEEL
swim-0.1.2.dist-info/entry_points.txt
swim-0.1.2.dist-info/metadata.json
swim-0.1.2.dist-info/top_level.txt
